__init__.py
gymnasium_rlate/__init__.py
gymnasium_rlate/cannon/Cannon.py
gymnasium_rlate/cannon/__init__.py
gymnasium_rlate/kbandit/KBandit.py
gymnasium_rlate/kbandit/__init__.py
gymnasium_rlate/pick_high/PickHigh.py
gymnasium_rlate/pick_high/__init__.py
gymnasium_rlate/pick_low/PickLow.py
gymnasium_rlate/pick_low/__init__.py
gymnasium_rlate/shuffler/Shuffler.py
gymnasium_rlate/shuffler/__init__.py
gymnasium_rlate/traffic_light/TrafficLight.py
gymnasium_rlate/traffic_light/__init__.py
rlate_env-0.0.17.dist-info/LICENSE
rlate_env-0.0.17.dist-info/METADATA
rlate_env-0.0.17.dist-info/WHEEL
rlate_env-0.0.17.dist-info/top_level.txt
rlate_env-0.0.17.dist-info/RECORD
