Metadata-Version: 2.1
Name: rlate-env
Version: 0.0.17
Summary: A collection of RL environments
Author-email: RLate <hello@rlate.space>
Project-URL: Homepage, https://github.com/RLate-Space/RL-Enviros
Project-URL: Issues, https://github.com/RLate-Space/RL-Enviros/issues
Classifier: Programming Language :: Python :: 3
Classifier: License :: OSI Approved :: MIT License
Classifier: Operating System :: OS Independent
Requires-Python: >=3.8
License-File: LICENSE
Requires-Dist: gymnasium >=0.29.1
Requires-Dist: numpy >=1.26.4
